[
  {
    "start": {
      "type": "date",
      "value": "2026-04-06"
    },
    "end": {
      "type": "date",
      "value": "2026-04-13"
    },
    "summary": "Reserved"
  },
  {
    "start": {
      "type": "date",
      "value": "2026-07-02"
    },
    "end": {
      "type": "date",
      "value": "2026-07-07"
    },
    "summary": "Reserved"
  },
  {
    "start": {
      "type": "date",
      "value": "2026-09-02"
    },
    "end": {
      "type": "date",
      "value": "2026-09-06"
    },
    "summary": "Reserved"
  },
  {
    "start": {
      "type": "date",
      "value": "2027-01-05"
    },
    "end": {
      "type": "date",
      "value": "2027-04-11"
    },
    "summary": "Airbnb (Not available)"
  }
]
